messenger_server_with_gui-0.0.2.data/scripts/server_run
server/__init__.py
server/run_server.py
server/commons/__init__.py
server/commons/commons.py
server/commons/decorators.py
server/commons/descryptors.py
server/commons/errors.py
server/commons/metaclasses.py
server/commons/utils.py
server/logs/__init__.py
server/server/__init__.py
server/server/add_user.py
server/server/config_window.py
server/server/delete_user.py
server/server/server_core.py
server/server/server_db.py
server/server/server_main_window.py
server/server/stat_window.py
messenger_server_with_gui-0.0.2.dist-info/METADATA
messenger_server_with_gui-0.0.2.dist-info/WHEEL
messenger_server_with_gui-0.0.2.dist-info/top_level.txt
messenger_server_with_gui-0.0.2.dist-info/RECORD
