Metadata-Version: 2.1
Name: messenger-server-with-gui
Version: 0.0.2
Summary: Messenger Server
Home-page: UNKNOWN
Author: Nataly Komarova
Author-email: shadowx110@yandex.ru
License: UNKNOWN
Platform: UNKNOWN
Requires-Dist: PyQt5
Requires-Dist: pycryptodome
Requires-Dist: pycryptodomex
Requires-Dist: sqlalchemy
